MANIFEST.in
README.md
setup.cfg
setup.py
versioneer.py
neptune_pytorch_lightning/__init__.py
neptune_pytorch_lightning/_version.py
neptune_pytorch_lightning.egg-info/PKG-INFO
neptune_pytorch_lightning.egg-info/SOURCES.txt
neptune_pytorch_lightning.egg-info/dependency_links.txt
neptune_pytorch_lightning.egg-info/not-zip-safe
neptune_pytorch_lightning.egg-info/requires.txt
neptune_pytorch_lightning.egg-info/top_level.txt
neptune_pytorch_lightning/impl/__init__.py