Metadata-Version: 2.1
Name: neptune-pytorch-lightning
Version: 0.9.7
Summary: Neptune.ai PyTorch Lightning integration library
Home-page: https://neptune.ai/
Author: neptune.ai
Author-email: contact@neptune.ai
License: Apache License 2.0
Project-URL: Tracker, https://github.com/neptune-ai/neptune-pytorch-lightning/issues
Project-URL: Source, https://github.com/neptune-ai/neptune-pytorch-lightning
Project-URL: Documentation, https://docs.neptune.ai/integrations-and-supported-tools/model-training/pytorch-lightning
Keywords: MLOps,ML Experiment Tracking,ML Model Registry,ML Model Store,ML Metadata Store
Platform: UNKNOWN
Classifier: Development Status :: 4 - Beta
Classifier: Environment :: Console
Classifier: Intended Audience :: Developers
Classifier: Intended Audience :: Science/Research
Classifier: License :: OSI Approved :: Apache Software License
Classifier: Natural Language :: English
Classifier: Operating System :: MacOS
Classifier: Operating System :: Microsoft :: Windows
Classifier: Operating System :: POSIX
Classifier: Operating System :: Unix
Classifier: Programming Language :: Python :: 3
Classifier: Programming Language :: Python :: 3.6
Classifier: Programming Language :: Python :: 3.7
Classifier: Programming Language :: Python :: 3.8
Classifier: Programming Language :: Python :: 3.9
Classifier: Topic :: Software Development :: Libraries :: Python Modules
Classifier: Programming Language :: Python :: Implementation :: CPython
Classifier: Topic :: Scientific/Engineering :: Artificial Intelligence
Provides-Extra: all
